testDataAnalysisModule/__init__.py
testDataAnalysisModule/fast_histogram.py
testDataAnalysisModule/setup.py
testDataAnalysisModule.egg-info/PKG-INFO
testDataAnalysisModule.egg-info/SOURCES.txt
testDataAnalysisModule.egg-info/dependency_links.txt
testDataAnalysisModule.egg-info/requires.txt
testDataAnalysisModule.egg-info/top_level.txt